cli.py
cosign.py
ctx.py
dockerutil.py
gitutil.py
http_requests.py
mailutil.py
makoutil.py
setup.py
signingserver.py
ccc/__init__.py
ccc/cfg.py
ccc/concourse.py
ccc/delivery.py
ccc/github.py
ccc/oci.py
ccc/secrets_server.py
ccc/slack.py
ci/VERSION
ci/__init__.py
ci/log.py
ci/paths.py
ci/util.py
cnudie/__init__.py
cnudie/access.py
cnudie/purge.py
cnudie/retrieve.py
cnudie/retrieve_async.py
cnudie/util.py
concourse/__init__.py
concourse/enumerator.py
concourse/factory.py
concourse/paths.py
concourse/replicator.py
concourse/util.py
concourse/validator.py
concourse/client/__init__.py
concourse/client/api.py
concourse/client/model.py
concourse/client/routes.py
concourse/client/util.py
concourse/model/__init__.py
concourse/model/base.py
concourse/model/job.py
concourse/model/pipeline.py
concourse/model/resources.py
concourse/model/step.py
concourse/model/traits/__init__.py
concourse/model/traits/component_descriptor.py
concourse/model/traits/cronjob.py
concourse/model/traits/draft_release.py
concourse/model/traits/images.py
concourse/model/traits/meta.py
concourse/model/traits/notifications.py
concourse/model/traits/options.py
concourse/model/traits/publish.py
concourse/model/traits/pullrequest.py
concourse/model/traits/release.py
concourse/model/traits/scheduling.py
concourse/model/traits/slack.py
concourse/model/traits/update_component_deps.py
concourse/model/traits/version.py
concourse/resources/LAST_RELEASED_TAG
concourse/resources/defaults.mako
concourse/resources/email.mako
concourse/resources/github.mako
concourse/resources/image.mako
concourse/resources/resource_types.mako
concourse/resources/time.mako
concourse/resources/variants.mako
concourse/steps/__init__.py
concourse/steps/build_oci_image.mako
concourse/steps/build_oci_image.py
concourse/steps/cfg_reporting.mako
concourse/steps/cfg_reporting.py
concourse/steps/component_descriptor.mako
concourse/steps/component_descriptor.py
concourse/steps/component_descriptor_util.py
concourse/steps/draft_release.mako
gardener_cicd_libs-1.2740.0.dist-info/LICENSE
gardener_cicd_libs-1.2740.0.dist-info/METADATA
gardener_cicd_libs-1.2740.0.dist-info/WHEEL
gardener_cicd_libs-1.2740.0.dist-info/top_level.txt
gardener_cicd_libs-1.2740.0.dist-info/RECORD
