Metadata-Version: 2.1
Name: gardener-cicd-libs
Version: 1.2740.0
Summary: Gardener CI/CD Libraries
Requires-Python: >=3.10
License-File: LICENSE
Requires-Dist: GitPython
Requires-Dist: Mako <2.0.0
Requires-Dist: Sphinx
Requires-Dist: awesomeversion
Requires-Dist: cachecontrol <1
Requires-Dist: cachetools
Requires-Dist: cryptography
Requires-Dist: dacite
Requires-Dist: deepmerge
Requires-Dist: deprecated
Requires-Dist: dockerfile-parse >=1.2
Requires-Dist: docutils
Requires-Dist: ensure
Requires-Dist: flake8
Requires-Dist: gardener-oci
Requires-Dist: gardener-oci >=1.2740.0
Requires-Dist: gardener-ocm >=1.2740.0
Requires-Dist: github3.py <5.0.0
Requires-Dist: html2text
Requires-Dist: jq
Requires-Dist: jsonpath-ng
Requires-Dist: jsonschema
Requires-Dist: pycryptodome
Requires-Dist: pyjwt
Requires-Dist: pylama
Requires-Dist: pylint
Requires-Dist: pytest
Requires-Dist: python-dateutil
Requires-Dist: python-gitlab
Requires-Dist: python-magic
Requires-Dist: pytimeparse
Requires-Dist: pyyaml
Requires-Dist: requests
Requires-Dist: ruamel.yaml ==0.17.21
Requires-Dist: semver
Requires-Dist: slack-sdk
Requires-Dist: sphinx-rtd-theme
Requires-Dist: sseclient-py
Requires-Dist: tabulate
Requires-Dist: termcolor
Requires-Dist: urllib3
Requires-Dist: yamllint
